testsetup/__init__.py
testsetup/hello.py
testsetup/config/t.json
testsetup/utilts/__init__.py
testsetup/utilts/print_info.py
myprinter-1.8.dist-info/LICENSE.txt
myprinter-1.8.dist-info/METADATA
myprinter-1.8.dist-info/WHEEL
myprinter-1.8.dist-info/top_level.txt
myprinter-1.8.dist-info/RECORD
