Metadata-Version: 2.1
Name: myprinter
Version: 1.8
Summary: Test setuptools
Home-page: http://pypi.python.org/pypi/myprinter2/
Author: fshenx
Author-email: 333@qq.com
License: MIT
Platform: UNKNOWN
